orshot/__init__.py
orshot/constants.py
orshot/exceptions.py
orshot/orshot.py
orshot/types.py
orshot-0.1.0.dist-info/METADATA
orshot-0.1.0.dist-info/WHEEL
orshot-0.1.0.dist-info/top_level.txt
orshot-0.1.0.dist-info/RECORD
