Metadata-Version: 2.4
Name: orshot
Version: 0.1.0
Summary: Orshot API SDK for Python.
Author-email: Rishi Mohan <iamrishi.ms@gmail.com>
Project-URL: Homepage, https://orshot.com
Classifier: License :: OSI Approved :: MIT License
Classifier: Programming Language :: Python
Classifier: Programming Language :: Python :: 3
Requires-Python: >=3.6
Requires-Dist: requests>=2.27.1
